iris_sample_data/__init__.py
iris_sample_data/_version.py
iris_sample_data/sample_data/A1B.2098.pp
iris_sample_data/sample_data/A1B_north_america.nc
iris_sample_data/sample_data/E1.2098.pp
iris_sample_data/sample_data/E1_north_america.nc
iris_sample_data/sample_data/NAME_output.txt
iris_sample_data/sample_data/SOI_Darwin.nc
iris_sample_data/sample_data/air_temp.pp
iris_sample_data/sample_data/atlantic_profiles.nc
iris_sample_data/sample_data/colpex.pp
iris_sample_data/sample_data/hybrid_height.nc
iris_sample_data/sample_data/mesh_C4_synthetic_float.nc
iris_sample_data/sample_data/orca2_votemper.nc
iris_sample_data/sample_data/ostia_monthly.nc
iris_sample_data/sample_data/polar_stereo.grib2
iris_sample_data/sample_data/pre-industrial.pp
iris_sample_data/sample_data/rotated_pole.nc
iris_sample_data/sample_data/space_weather.nc
iris_sample_data/sample_data/toa_brightness_stereographic.nc
iris_sample_data/sample_data/uk_hires.pp
iris_sample_data/sample_data/vlstr_type.nc
iris_sample_data/sample_data/wind_speed_lake_victoria.pp
iris_sample_data/sample_data/GloSea4/ensemble_000.pp
iris_sample_data/sample_data/GloSea4/ensemble_001.pp
iris_sample_data/sample_data/GloSea4/ensemble_002.pp
iris_sample_data/sample_data/GloSea4/ensemble_003.pp
iris_sample_data/sample_data/GloSea4/ensemble_004.pp
iris_sample_data/sample_data/GloSea4/ensemble_005.pp
iris_sample_data/sample_data/GloSea4/ensemble_007.pp
iris_sample_data/sample_data/GloSea4/ensemble_008.pp
iris_sample_data/sample_data/GloSea4/ensemble_009.pp
iris_sample_data/sample_data/GloSea4/ensemble_010.pp
iris_sample_data/sample_data/GloSea4/ensemble_011.pp
iris_sample_data/sample_data/GloSea4/ensemble_012.pp
iris_sample_data/sample_data/GloSea4/ensemble_013.pp
iris_sample_data/sample_data/NEMO/nemo_1m_20150101-20150201_grid-T.nc
iris_sample_data/sample_data/NEMO/nemo_1m_20150201-20150301_grid-T.nc
iris_sample_data/sample_data/NEMO/nemo_1m_20150301-20150401_grid-T.nc
iris_sample_data-2.5.2.dist-info/METADATA
iris_sample_data-2.5.2.dist-info/WHEEL
iris_sample_data-2.5.2.dist-info/top_level.txt
iris_sample_data-2.5.2.dist-info/RECORD
