Metadata-Version: 2.2
Name: iris-sample-data
Version: 2.5.2
Summary: Iris sample data
Home-page: https://github.com/SciTools/iris-sample-data
Download-URL: https://github.com/SciTools/iris-sample-data
Author: SciTools Developers
Author-email: scitools-iris-dev@googlegroups.com
License: Open Government
Project-URL: Code, https://github.com/SciTools/iris-sample-data
Project-URL: Issues, https://github.com/SciTools/iris-sample-data/issues
Keywords: cf-metadata,earth-science,grib,netcdf,meteorology,oceanography,ugrid
Classifier: Development Status :: 5 - Production/Stable
Classifier: Intended Audience :: Science/Research
Classifier: License :: Freely Distributable
Classifier: Operating System :: MacOS
Classifier: Operating System :: POSIX
Classifier: Operating System :: POSIX :: Linux
Classifier: Operating System :: Unix
Classifier: Programming Language :: Python
Classifier: Programming Language :: Python :: 3 :: Only
Classifier: Programming Language :: Python :: 3.7
Classifier: Programming Language :: Python :: 3.8
Classifier: Programming Language :: Python :: Implementation :: CPython
Classifier: Topic :: Scientific/Engineering
Classifier: Topic :: Scientific/Engineering :: Atmospheric Science
Requires-Python: >=3.7
Dynamic: download-url
